Workbook

Sheet Assumptions
A1: Parameters | B1: Value
A2: Annual Queries | B2: =500000*12 -> 6000000
A3: Human Call Cost ($) | B3: 4
A4: AI Cost per Interaction ($) | B4: 0.8
A5: Automation Rate (%) | B5: 0.6
A6: Discount Rate (%) | B6: 0.1
A7: Annual Query Growth (%) | B7: 0.05

Sheet Cost Comparison
A1: 3-Year Forecast
C2: Year 1 | D2: Year 2 | E2: Year 3
A3: Yearly Queries | C3: =Assumptions!B2 -> 6000000 | D3: =C3*(1+Assumptions!B7) -> 6300000 | E3: =D3*(1+Assumptions!B7) -> 6615000
A5: Current Annual Cost($) | C5: =Assumptions!B2*Assumptions!B3 -> 24000000 | D5: =D3*Assumptions!B3 -> 25200000 | E5: =E3*Assumptions!B3 -> 26460000
A6: Annaul AI Cost ($) | C6: =Assumptions!B5*Assumptions!B4*C3+Assumptions!B3*C3*(1-Assumptions!B5) -> 12480000 | D6: =Assumptions!B5*Assumptions!B4*'Cost Comparison'!D3+Assumptions!B3*'Cost Comparison'!D3*(1-Assumptions!B5) -> 13104000 | E6: =Assumptions!B5*Assumptions!B4*'Cost Comparison'!E3+Assumptions!B3*'Cost Comparison'!E3*(1-Assumptions!B5) -> 13759200
A7: Annual Savings ($) | C7: =C5-C6 -> 11520000 | D7: =D5-D6 -> 12096000 | E7: =E5-E6 -> 12700800
A9: NPV ($) | C9: =C7/(1+Assumptions!B6)^1 -> 10472727 | D9: =D7/(1+Assumptions!B6)^2 -> 9996694.2 | E9: =E7/(1+Assumptions!B6)^3 -> 9542299
A11: Total NPV ($) | C11: =SUM(C9:E9) -> 30011721 | D11: ($ 30 million)
A13: Implementation Cost(One-Time) ($) | E13: =5000000 -> 5000000
A15: NET NPV | B15: =C11-E13 -> 25011721 | C15: ($ 25 Million)
A16: Payback Period | C16: =E13/C7 -> 0.43402778 | D16: 5 months(approx.)

Sheet Sensitivity Analysis
A1: Automation % | B1: =E1 -> Annual Savings ($) | C1: Annual Cost ($) | D1: Annual AI Cost ($) | E1: Annual Savings ($)
A2: 0.4 | B2: =E2 -> 7680000 | C2: ='Cost Comparison'!$C$5 -> 24000000 | D2: =A2*Assumptions!B4*'Cost Comparison'!C3+Assumptions!B3*'Cost Comparison'!C3*(1-A2) -> 16320000 | E2: =C2-D2 -> 7680000
A3: 0.5 | B3: =E3 -> 9600000 | C3: ='Cost Comparison'!$C$5 -> 24000000 | D3: =A3*Assumptions!B4*'Cost Comparison'!C3+Assumptions!B3*'Cost Comparison'!C3*(1-A3) -> 14400000 | E3: =C3-D3 -> 9600000
A4: 0.6 | B4: =E4 -> 11520000 | C4: ='Cost Comparison'!$C$5 -> 24000000 | D4: =A4*Assumptions!B4*'Cost Comparison'!C3+Assumptions!B3*'Cost Comparison'!C3*(1-A4) -> 12480000 | E4: =C4-D4 -> 11520000
A5: 0.7 | B5: =E5 -> 13440000 | C5: ='Cost Comparison'!$C$5 -> 24000000 | D5: =A5*Assumptions!B4*'Cost Comparison'!C3+Assumptions!B3*'Cost Comparison'!C3*(1-A5) -> 10560000 | E5: =C5-D5 -> 13440000
A6: 0.8 | B6: =E6 -> 15360000 | C6: ='Cost Comparison'!$C$5 -> 24000000 | D6: =A6*Assumptions!B4*'Cost Comparison'!C3+Assumptions!B3*'Cost Comparison'!C3*(1-A6) -> 8640000 | E6: =C6-D6 -> 15360000

Sheet Executive Summary
A1: Objective
A2: Evaluate the financial impact of AI-driven customer service automation in a mid-tier bank.
A5: Key Assumptions
A7: 1. Annual Queries (Year 1): 6,000,000
A8: 2. Human Cost per Call: $4
A9: 3. AI Cost per Interaction: $0.8
A10: 4. Automation Rate (Base Case): 60%
A11: 5. Discount Rate: 10%
A14: Financial Impact (Base Case – 60% Automation)
A16: 1. Year 1 Cost Reduction: $11.52M
A17: 2. 3-Year Discounted Savings (NPV): ~$30M
A18: 3. Estimated Payback Period: < 1 year (if implementation cost ≤ $10M)
... A33: Even under conservative automation (40%), annual savings remain positive at ~$7.7M, indicating downside protection.
